[
  {
    "name": "CreateComponent",
    "evaluated": false,
    "allowed": false,
    "prefix": "amplifyuibuilder",
    "service": "AWS Amplify UI Builder",
    "serviceAware": true,
    "resourceEnabled": false,
    "deniedByOrganization": false,
    "supportedResources": [
      {
        "Name": "ARN",
        "ARN": "*",
        "ContextKeys": [],
        "ContextKeyStrings": [],
        "isRequired": true,
        "ContextKeysRef": []
      }
    ]
  },
  {
    "name": "CreateTheme",
    "evaluated": false,
    "allowed": false,
    "prefix": "amplifyuibuilder",
    "service": "AWS Amplify UI Builder",
    "serviceAware": true,
    "resourceEnabled": false,
    "deniedByOrganization": false,
    "supportedResources": [
      {
        "Name": "ARN",
        "ARN": "*",
        "ContextKeys": [],
        "ContextKeyStrings": [],
        "isRequired": true,
        "ContextKeysRef": []
      }
    ]
  },
  {
    "name": "DeleteComponent",
    "evaluated": false,
    "allowed": false,
    "prefix": "amplifyuibuilder",
    "service": "AWS Amplify UI Builder",
    "serviceAware": true,
    "resourceEnabled": true,
    "deniedByOrganization": false,
    "requiredResourceNames": [
      "ComponentResource"
    ],
    "supportedResources": [
      {
        "Name": "ComponentResource",
        "ARN": "arn:aws:amplifyuibuilder:${Region}:${Account}:app/${AppId}/environment/${EnvironmentName}/components/${Id}",
        "RegEx": "^arn:aws:amplifyuibuilder:${Region}:${Account}:app/.+?/environment/.+?/components/.+?",
        "ContextKeys": [
          "amplifyuibuilder:AppId",
          "amplifyuibuilder:EnvironmentName",
          "amplifyuibuilder:ComponentsId",
          "aws:ResourceTag/${TagKey}"
        ],
        "ContextKeyStrings": [
          "amplifyuibuilder:componentsid",
          "aws:resourcetag/${tagkey}",
          "amplifyuibuilder:environmentname",
          "amplifyuibuilder:appid"
        ],
        "isRequired": true
      }
    ],
    "scenarios": [],
    "contextKeys": []
  },
  {
    "name": "DeleteTheme",
    "evaluated": false,
    "allowed": false,
    "prefix": "amplifyuibuilder",
    "service": "AWS Amplify UI Builder",
    "serviceAware": true,
    "resourceEnabled": true,
    "deniedByOrganization": false,
    "requiredResourceNames": [
      "ThemeResource"
    ],
    "supportedResources": [
      {
        "Name": "ThemeResource",
        "ARN": "arn:aws:amplifyuibuilder:${Region}:${Account}:app/${AppId}/environment/${EnvironmentName}/themes/${Id}",
        "RegEx": "^arn:aws:amplifyuibuilder:${Region}:${Account}:app/.+?/environment/.+?/themes/.+?",
        "ContextKeys": [
          "amplifyuibuilder:AppId",
          "amplifyuibuilder:EnvironmentName",
          "amplifyuibuilder:ThemesId",
          "aws:ResourceTag/${TagKey}"
        ],
        "ContextKeyStrings": [
          "aws:resourcetag/${tagkey}",
          "amplifyuibuilder:themesid",
          "amplifyuibuilder:environmentname",
          "amplifyuibuilder:appid"
        ],
        "isRequired": true
      }
    ],
    "scenarios": [],
    "contextKeys": []
  },
  {
    "name": "ExchangeCodeForToken",
    "evaluated": false,
    "allowed": false,
    "prefix": "amplifyuibuilder",
    "service": "AWS Amplify UI Builder",
    "serviceAware": true,
    "resourceEnabled": false,
    "deniedByOrganization": false,
    "supportedResources": [
      {
        "Name": "ARN",
        "ARN": "*",
        "ContextKeys": [],
        "ContextKeyStrings": [],
        "isRequired": true,
        "ContextKeysRef": []
      }
    ]
  },
  {
    "name": "ExportComponents",
    "evaluated": false,
    "allowed": false,
    "prefix": "amplifyuibuilder",
    "service": "AWS Amplify UI Builder",
    "serviceAware": true,
    "resourceEnabled": false,
    "deniedByOrganization": false,
    "supportedResources": [
      {
        "Name": "ARN",
        "ARN": "*",
        "ContextKeys": [],
        "ContextKeyStrings": [],
        "isRequired": true,
        "ContextKeysRef": []
      }
    ]
  },
  {
    "name": "ExportThemes",
    "evaluated": false,
    "allowed": false,
    "prefix": "amplifyuibuilder",
    "service": "AWS Amplify UI Builder",
    "serviceAware": true,
    "resourceEnabled": false,
    "deniedByOrganization": false,
    "supportedResources": [
      {
        "Name": "ARN",
        "ARN": "*",
        "ContextKeys": [],
        "ContextKeyStrings": [],
        "isRequired": true,
        "ContextKeysRef": []
      }
    ]
  },
  {
    "name": "GetComponent",
    "evaluated": false,
    "allowed": false,
    "prefix": "amplifyuibuilder",
    "service": "AWS Amplify UI Builder",
    "serviceAware": true,
    "resourceEnabled": true,
    "deniedByOrganization": false,
    "requiredResourceNames": [
      "ComponentResource"
    ],
    "supportedResources": [
      {
        "Name": "ComponentResource",
        "ARN": "arn:aws:amplifyuibuilder:${Region}:${Account}:app/${AppId}/environment/${EnvironmentName}/components/${Id}",
        "RegEx": "^arn:aws:amplifyuibuilder:${Region}:${Account}:app/.+?/environment/.+?/components/.+?",
        "ContextKeys": [
          "amplifyuibuilder:AppId",
          "amplifyuibuilder:EnvironmentName",
          "amplifyuibuilder:ComponentsId",
          "aws:ResourceTag/${TagKey}"
        ],
        "ContextKeyStrings": [
          "amplifyuibuilder:componentsid",
          "aws:resourcetag/${tagkey}",
          "amplifyuibuilder:environmentname",
          "amplifyuibuilder:appid"
        ],
        "isRequired": true
      }
    ],
    "scenarios": [],
    "contextKeys": []
  },
  {
    "name": "GetTheme",
    "evaluated": false,
    "allowed": false,
    "prefix": "amplifyuibuilder",
    "service": "AWS Amplify UI Builder",
    "serviceAware": true,
    "resourceEnabled": true,
    "deniedByOrganization": false,
    "requiredResourceNames": [
      "ThemeResource"
    ],
    "supportedResources": [
      {
        "Name": "ThemeResource",
        "ARN": "arn:aws:amplifyuibuilder:${Region}:${Account}:app/${AppId}/environment/${EnvironmentName}/themes/${Id}",
        "RegEx": "^arn:aws:amplifyuibuilder:${Region}:${Account}:app/.+?/environment/.+?/themes/.+?",
        "ContextKeys": [
          "amplifyuibuilder:AppId",
          "amplifyuibuilder:EnvironmentName",
          "amplifyuibuilder:ThemesId",
          "aws:ResourceTag/${TagKey}"
        ],
        "ContextKeyStrings": [
          "aws:resourcetag/${tagkey}",
          "amplifyuibuilder:themesid",
          "amplifyuibuilder:environmentname",
          "amplifyuibuilder:appid"
        ],
        "isRequired": true
      }
    ],
    "scenarios": [],
    "contextKeys": []
  },
  {
    "name": "ListComponents",
    "evaluated": false,
    "allowed": false,
    "prefix": "amplifyuibuilder",
    "service": "AWS Amplify UI Builder",
    "serviceAware": true,
    "resourceEnabled": false,
    "deniedByOrganization": false,
    "supportedResources": [
      {
        "Name": "ARN",
        "ARN": "*",
        "ContextKeys": [],
        "ContextKeyStrings": [],
        "isRequired": true,
        "ContextKeysRef": []
      }
    ]
  },
  {
    "name": "ListTagsForResource",
    "evaluated": false,
    "allowed": false,
    "prefix": "amplifyuibuilder",
    "service": "AWS Amplify UI Builder",
    "serviceAware": true,
    "resourceEnabled": true,
    "deniedByOrganization": false,
    "supportedResources": [
      {
        "Name": "ThemeResource",
        "ARN": "arn:aws:amplifyuibuilder:${Region}:${Account}:app/${AppId}/environment/${EnvironmentName}/themes/${Id}",
        "RegEx": "^arn:aws:amplifyuibuilder:${Region}:${Account}:app/.+?/environment/.+?/themes/.+?",
        "ContextKeys": [
          "amplifyuibuilder:AppId",
          "amplifyuibuilder:EnvironmentName",
          "amplifyuibuilder:ThemesId",
          "aws:ResourceTag/${TagKey}"
        ],
        "ContextKeyStrings": [
          "aws:resourcetag/${tagkey}",
          "amplifyuibuilder:themesid",
          "amplifyuibuilder:environmentname",
          "amplifyuibuilder:appid"
        ],
        "isRequired": false
      },
      {
        "Name": "ComponentResource",
        "ARN": "arn:aws:amplifyuibuilder:${Region}:${Account}:app/${AppId}/environment/${EnvironmentName}/components/${Id}",
        "RegEx": "^arn:aws:amplifyuibuilder:${Region}:${Account}:app/.+?/environment/.+?/components/.+?",
        "ContextKeys": [
          "amplifyuibuilder:AppId",
          "amplifyuibuilder:EnvironmentName",
          "amplifyuibuilder:ComponentsId",
          "aws:ResourceTag/${TagKey}"
        ],
        "ContextKeyStrings": [
          "amplifyuibuilder:componentsid",
          "aws:resourcetag/${tagkey}",
          "amplifyuibuilder:environmentname",
          "amplifyuibuilder:appid"
        ],
        "isRequired": false
      }
    ],
    "scenarios": [],
    "contextKeys": []
  },
  {
    "name": "ListThemes",
    "evaluated": false,
    "allowed": false,
    "prefix": "amplifyuibuilder",
    "service": "AWS Amplify UI Builder",
    "serviceAware": true,
    "resourceEnabled": false,
    "deniedByOrganization": false,
    "supportedResources": [
      {
        "Name": "ARN",
        "ARN": "*",
        "ContextKeys": [],
        "ContextKeyStrings": [],
        "isRequired": true,
        "ContextKeysRef": []
      }
    ]
  },
  {
    "name": "RefreshToken",
    "evaluated": false,
    "allowed": false,
    "prefix": "amplifyuibuilder",
    "service": "AWS Amplify UI Builder",
    "serviceAware": true,
    "resourceEnabled": false,
    "deniedByOrganization": false,
    "supportedResources": [
      {
        "Name": "ARN",
        "ARN": "*",
        "ContextKeys": [],
        "ContextKeyStrings": [],
        "isRequired": true,
        "ContextKeysRef": []
      }
    ]
  },
  {
    "name": "TagResource",
    "evaluated": false,
    "allowed": false,
    "prefix": "amplifyuibuilder",
    "service": "AWS Amplify UI Builder",
    "serviceAware": true,
    "resourceEnabled": true,
    "deniedByOrganization": false,
    "supportedResources": [
      {
        "Name": "ThemeResource",
        "ARN": "arn:aws:amplifyuibuilder:${Region}:${Account}:app/${AppId}/environment/${EnvironmentName}/themes/${Id}",
        "RegEx": "^arn:aws:amplifyuibuilder:${Region}:${Account}:app/.+?/environment/.+?/themes/.+?",
        "ContextKeys": [
          "amplifyuibuilder:AppId",
          "amplifyuibuilder:EnvironmentName",
          "amplifyuibuilder:ThemesId",
          "aws:ResourceTag/${TagKey}"
        ],
        "ContextKeyStrings": [
          "aws:resourcetag/${tagkey}",
          "amplifyuibuilder:themesid",
          "amplifyuibuilder:environmentname",
          "amplifyuibuilder:appid"
        ],
        "isRequired": false
      },
      {
        "Name": "ComponentResource",
        "ARN": "arn:aws:amplifyuibuilder:${Region}:${Account}:app/${AppId}/environment/${EnvironmentName}/components/${Id}",
        "RegEx": "^arn:aws:amplifyuibuilder:${Region}:${Account}:app/.+?/environment/.+?/components/.+?",
        "ContextKeys": [
          "amplifyuibuilder:AppId",
          "amplifyuibuilder:EnvironmentName",
          "amplifyuibuilder:ComponentsId",
          "aws:ResourceTag/${TagKey}"
        ],
        "ContextKeyStrings": [
          "amplifyuibuilder:componentsid",
          "aws:resourcetag/${tagkey}",
          "amplifyuibuilder:environmentname",
          "amplifyuibuilder:appid"
        ],
        "isRequired": false
      }
    ],
    "scenarios": [],
    "contextKeys": [
      {
        "Name": "aws:TagKeys",
        "Type": "ArrayOfString",
        "DocPageRel": "https://docs.aws.amazon.com/IAM/latest/UserGuide/reference_policies_condition-keys.html#condition-keys-tagkeys",
        "DocPage": "${DocHomeURL}IAM/latest/UserGuide/reference_policies_condition-keys.html#condition-keys-tagkeys",
        "Description": "Filters access based on the tag keys that are passed in the request"
      },
      {
        "Name": "aws:RequestTag/${TagKey}",
        "Type": "String",
        "DocPageRel": "https://docs.aws.amazon.com/IAM/latest/UserGuide/reference_policies_condition-keys.html#condition-keys-requesttag",
        "DocPage": "${DocHomeURL}IAM/latest/UserGuide/reference_policies_condition-keys.html#condition-keys-requesttag",
        "Description": "Filters access based on the tags that are passed in the request"
      }
    ]
  },
  {
    "name": "UntagResource",
    "evaluated": false,
    "allowed": false,
    "prefix": "amplifyuibuilder",
    "service": "AWS Amplify UI Builder",
    "serviceAware": true,
    "resourceEnabled": true,
    "deniedByOrganization": false,
    "supportedResources": [
      {
        "Name": "ThemeResource",
        "ARN": "arn:aws:amplifyuibuilder:${Region}:${Account}:app/${AppId}/environment/${EnvironmentName}/themes/${Id}",
        "RegEx": "^arn:aws:amplifyuibuilder:${Region}:${Account}:app/.+?/environment/.+?/themes/.+?",
        "ContextKeys": [
          "amplifyuibuilder:AppId",
          "amplifyuibuilder:EnvironmentName",
          "amplifyuibuilder:ThemesId",
          "aws:ResourceTag/${TagKey}"
        ],
        "ContextKeyStrings": [
          "aws:resourcetag/${tagkey}",
          "amplifyuibuilder:themesid",
          "amplifyuibuilder:environmentname",
          "amplifyuibuilder:appid"
        ],
        "isRequired": false
      },
      {
        "Name": "ComponentResource",
        "ARN": "arn:aws:amplifyuibuilder:${Region}:${Account}:app/${AppId}/environment/${EnvironmentName}/components/${Id}",
        "RegEx": "^arn:aws:amplifyuibuilder:${Region}:${Account}:app/.+?/environment/.+?/components/.+?",
        "ContextKeys": [
          "amplifyuibuilder:AppId",
          "amplifyuibuilder:EnvironmentName",
          "amplifyuibuilder:ComponentsId",
          "aws:ResourceTag/${TagKey}"
        ],
        "ContextKeyStrings": [
          "amplifyuibuilder:componentsid",
          "aws:resourcetag/${tagkey}",
          "amplifyuibuilder:environmentname",
          "amplifyuibuilder:appid"
        ],
        "isRequired": false
      }
    ],
    "scenarios": [],
    "contextKeys": [
      {
        "Name": "aws:TagKeys",
        "Type": "ArrayOfString",
        "DocPageRel": "https://docs.aws.amazon.com/IAM/latest/UserGuide/reference_policies_condition-keys.html#condition-keys-tagkeys",
        "DocPage": "${DocHomeURL}IAM/latest/UserGuide/reference_policies_condition-keys.html#condition-keys-tagkeys",
        "Description": "Filters access based on the tag keys that are passed in the request"
      }
    ]
  },
  {
    "name": "UpdateComponent",
    "evaluated": false,
    "allowed": false,
    "prefix": "amplifyuibuilder",
    "service": "AWS Amplify UI Builder",
    "serviceAware": true,
    "resourceEnabled": true,
    "deniedByOrganization": false,
    "requiredResourceNames": [
      "ComponentResource"
    ],
    "supportedResources": [
      {
        "Name": "ComponentResource",
        "ARN": "arn:aws:amplifyuibuilder:${Region}:${Account}:app/${AppId}/environment/${EnvironmentName}/components/${Id}",
        "RegEx": "^arn:aws:amplifyuibuilder:${Region}:${Account}:app/.+?/environment/.+?/components/.+?",
        "ContextKeys": [
          "amplifyuibuilder:AppId",
          "amplifyuibuilder:EnvironmentName",
          "amplifyuibuilder:ComponentsId",
          "aws:ResourceTag/${TagKey}"
        ],
        "ContextKeyStrings": [
          "amplifyuibuilder:componentsid",
          "aws:resourcetag/${tagkey}",
          "amplifyuibuilder:environmentname",
          "amplifyuibuilder:appid"
        ],
        "isRequired": true
      }
    ],
    "scenarios": [],
    "contextKeys": []
  },
  {
    "name": "UpdateTheme",
    "evaluated": false,
    "allowed": false,
    "prefix": "amplifyuibuilder",
    "service": "AWS Amplify UI Builder",
    "serviceAware": true,
    "resourceEnabled": true,
    "deniedByOrganization": false,
    "requiredResourceNames": [
      "ThemeResource"
    ],
    "supportedResources": [
      {
        "Name": "ThemeResource",
        "ARN": "arn:aws:amplifyuibuilder:${Region}:${Account}:app/${AppId}/environment/${EnvironmentName}/themes/${Id}",
        "RegEx": "^arn:aws:amplifyuibuilder:${Region}:${Account}:app/.+?/environment/.+?/themes/.+?",
        "ContextKeys": [
          "amplifyuibuilder:AppId",
          "amplifyuibuilder:EnvironmentName",
          "amplifyuibuilder:ThemesId",
          "aws:ResourceTag/${TagKey}"
        ],
        "ContextKeyStrings": [
          "aws:resourcetag/${tagkey}",
          "amplifyuibuilder:themesid",
          "amplifyuibuilder:environmentname",
          "amplifyuibuilder:appid"
        ],
        "isRequired": true
      }
    ],
    "scenarios": [],
    "contextKeys": []
  }
]